{
  "id": 305389,
  "username": "pledru",
  "resource_state": 3,
  "firstname": "Pascal",
  "lastname": "Ledru",
  "city": "Boulder",
  "state": "CO",
  "country": "United States",
  "sex": "M",
  "premium": true,
  "created_at": "2012-03-04T23:24:14Z",
  "updated_at": "2018-04-15T03:37:34Z",
  "badge_type_id": 1,
  "profile_medium": "https://dgalywyr863hv.cloudfront.net/pictures/athletes/305389/1164096/4/medium.jpg",
  "profile": "https://dgalywyr863hv.cloudfront.net/pictures/athletes/305389/1164096/4/large.jpg",
  "friend": null,
  "follower": null,
  "email": "pascal.ledru@gmail.com",
  "follower_count": 35,
  "friend_count": 25,
  "mutual_friend_count": 0,
  "athlete_type": 0,
  "date_preference": "%m/%d/%Y",
  "measurement_preference": "feet",
  "clubs": [{
    "id": 134155,
    "resource_state": 2,
    "name": "Paris-Brest-Paris Randonneur",
    "profile_medium": "https://dgalywyr863hv.cloudfront.net/pictures/clubs/134155/2669527/2/medium.jpg",
    "profile": "https://dgalywyr863hv.cloudfront.net/pictures/clubs/134155/2669527/2/large.jpg",
    "cover_photo": "https://dgalywyr863hv.cloudfront.net/pictures/clubs/134155/5332211/1/large.jpg",
    "cover_photo_small": "https://dgalywyr863hv.cloudfront.net/pictures/clubs/134155/5332211/1/small.jpg",
    "sport_type": "cycling",
    "city": "Montigny-le-Bretonneux",
    "state": "Île-de-France",
    "country": "France",
    "private": false,
    "member_count": 2114,
    "featured": false,
    "verified": true,
    "url": "parisbrest",
    "membership": "member",
    "admin": false,
    "owner": false
  }, {
    "id": 3674,
    "resource_state": 2,
    "name": "Rocky Mountain Cycling Club",
    "profile_medium": "https://dgalywyr863hv.cloudfront.net/pictures/clubs/3674/81697/2/medium.jpg",
    "profile": "https://dgalywyr863hv.cloudfront.net/pictures/clubs/3674/81697/2/large.jpg",
    "cover_photo": "https://dgalywyr863hv.cloudfront.net/pictures/clubs/3674/4451418/4/large.jpg",
    "cover_photo_small": "https://dgalywyr863hv.cloudfront.net/pictures/clubs/3674/4451418/4/small.jpg",
    "sport_type": "cycling",
    "city": "Denver",
    "state": "Colorado",
    "country": "United States",
    "private": true,
    "member_count": 80,
    "featured": false,
    "verified": false,
    "url": "rocky-mountain-cycling-club",
    "membership": "member",
    "admin": false,
    "owner": false
  }, {
    "id": 108957,
    "resource_state": 2,
    "name": "한국란도너스  Korea Randonneurs",
    "profile_medium": "https://dgalywyr863hv.cloudfront.net/pictures/clubs/108957/1955894/1/medium.jpg",
    "profile": "https://dgalywyr863hv.cloudfront.net/pictures/clubs/108957/1955894/1/large.jpg",
    "cover_photo": "https://dgalywyr863hv.cloudfront.net/pictures/clubs/108957/5583746/2/large.jpg",
    "cover_photo_small": "https://dgalywyr863hv.cloudfront.net/pictures/clubs/108957/5583746/2/small.jpg",
    "sport_type": "cycling",
    "city": "",
    "state": "",
    "country": "대한민국",
    "private": false,
    "member_count": 2022,
    "featured": false,
    "verified": false,
    "url": "Kora",
    "membership": "member",
    "admin": false,
    "owner": false
  }, {
    "id": 328066,
    "resource_state": 2,
    "name": "Project Hero Denver Hub",
    "profile_medium": "https://dgalywyr863hv.cloudfront.net/pictures/clubs/328066/7721623/1/medium.jpg",
    "profile": "https://dgalywyr863hv.cloudfront.net/pictures/clubs/328066/7721623/1/large.jpg",
    "cover_photo": null,
    "cover_photo_small": null,
    "sport_type": "cycling",
    "city": "Denver",
    "state": "Colorado",
    "country": "United States",
    "private": false,
    "member_count": 9,
    "featured": false,
    "verified": false,
    "url": "projectherodenverhub",
    "membership": "member",
    "admin": false,
    "owner": false
  }],
  "ftp": null,
  "weight": 61.2349,
  "bikes": [{
    "id": "b4051831",
    "primary": true,
    "name": "The Korea bike",
    "resource_state": 2,
    "distance": 9460414
  }, {
    "id": "b4051832",
    "primary": false,
    "name": "The PBP Bike #1",
    "resource_state": 2,
    "distance": 84810
  }],
  "shoes": []
}
